{
  "theme": {
    "preset": "warm-sunrise",
    "mode": "light",
    "colors": {
      "primary": "#e8772e",
      "secondary": "#c44a3a",
      "accent": "#d4a12e",
      "background": "#faf8f5",
      "surface": "#f5f0eb",
      "text": "#2d1f12",
      "muted": "#8a7a6d",
      "border": "#e8e0d8"
    },
    "typography": {
      "fontFamily": "DM Sans",
      "headingFamily": "DM Sans",
      "headingWeight": 700,
      "baseSize": "16px"
    },
    "spacing": {
      "sectionPadding": "64px",
      "containerMaxWidth": "1200px",
      "componentGap": "32px"
    },
    "borderRadius": "16px"
  },
  "sections": [
    {
      "id": "hero-01",
      "variant": "split-right",
      "layout": {
        "display": "flex",
        "direction": "row",
        "align": "center",
        "gap": "48px",
        "padding": "64px",
        "maxWidth": "1200px"
      },
      "style": {
        "background": "#faf8f5",
        "color": "#2d1f12",
        "fontFamily": "DM Sans"
      },
      "components": [
        { "id": "heroImage", "props": { "url": "https://images.unsplash.com/photo-1522071820081-009f0129c71c?w=800&auto=format", "alt": "Team workspace", "aspect": "4:3" }, "enabled": true }
      ]
    }
  ]
}
